Workbook

Sheet Resumen
A1: ROKKO Cotizador - Plan integral del proyecto
A2: Recopilacion desde cero: desarrollo, BD, Supabase, modelos 3D, Gantt, costos y flujo de caja. Sin Docker ni maquina virtual.
A4: Estado actual | B4: Proyecto funcional al 94-95%, con lint/build OK y visualizador 3D prenda-only.
A5: Stack | B5: Next.js 16, React 19, Tailwind v4, Supabase, Three/R3F, Fabric, Resend.
A6: Equipo | B6: Un programador full-stack.
A7: Duracion estimada | B7: 12 semanas / 410 horas estimadas.
A8: Costo desarrollo estimado | B8: ='Costos Proyecto'!F19 -> 7380000
A9: Costos unicos adicionales | B9: ='Costos Proyecto'!F20 -> 195000
A10: Costo operativo mensual base | B10: ='Costos Proyecto'!F21 -> 568000
A11: Proximo foco | B11: Optimizar selector de colores y carga 3D; QA end-to-end final.
A12: Exclusiones | B12: No incluye Docker, maquina virtual ni proyecto radio.

Sheet Supuestos
A1: Supuestos editables
A2: Ajusta tarifas, conversion, ticket promedio y costos para recalcular el modelo.
A4: Supuesto | B4: Valor
A5: Moneda | B5: CLP
A6: Programadores | B6: 1
A7: Tarifa programador por hora | B7: 18000
A8: Horas estimadas totales | B8: 410
A9: Duracion proyecto | B9: 12 semanas
A10: IVA | B10: 0.19
A11: Anticipo recomendado cliente | B11: 0.6
A12: Saldo contra entrega | B12: 0.4
A13: Margen bruto objetivo | B13: 0.45
A14: Ticket promedio esperado | B14: 650000
A15: Cotizaciones mensuales objetivo | B15: 18
A16: Conversion esperada | B16: 0.28
A17: Pedidos mensuales estimados | B17: 5

Sheet Modelo Canvas
A1: Modelo Canvas ROKKO
A2: Modelo de negocio del cotizador y venta de uniformes corporativos.
A4: Bloque | B4: Descripcion
A5: Propuesta de valor | B5: Cotizador profesional para uniformes corporativos con productos, colores, tallas, logo, cotizacion y visualizador 3D de prenda.
A6: Clientes | B6: Empresas, colegios, instituciones, restaurantes, constructoras, eventos y organizaciones que compran vestuario por volumen.
A7: Canales | B7: Sitio web, cotizador online, email, WhatsApp, ventas directas y panel admin.
A8: Relacion con clientes | B8: Autoservicio inicial, seguimiento humano, respuesta comercial, ajustes y cierre asistido.
A9: Ingresos | B9: Venta de prendas, personalizacion, pedidos mayoristas, reposiciones y contratos recurrentes.
A10: Recursos clave | B10: Catalogo, imagenes, modelos 3D, Supabase, Vercel, Resend, marca ROKKO, proveedor textil y programador.
A11: Actividades clave | B11: Mantener catalogo, responder cotizaciones, producir/personalizar, cobrar, entregar y optimizar conversion.
A12: Socios clave | B12: Proveedores textiles, talleres de bordado/estampado, courier, Supabase, Vercel, Resend.
A13: Costos | B13: Programacion, hosting, BD, email, dominio, imagenes, modelos 3D, mantencion, produccion y despacho.

Sheet PDCA
A1: Ciclo PDCA del proyecto
A2: Planificar, hacer, verificar y actuar para cierre y mejora continua.
A4: Fase | B4: Accion | C4: Resultado esperado
A5: Planificar | B5: Definir producto comercial, BD, flujo de cotizacion, admin, visualizador 3D y reglas de negocio. | C5: Alcance claro, backlog, supuestos de costos, estructura de datos.
A6: Hacer | B6: Construir Next.js, Supabase, admin, cotizador, emails, modelos GLB, visualizador prenda-only y limpieza tecnica. | C6: Sistema funcional con build/lint OK.
A7: Verificar | B7: Probar rutas, build, lint, flujo publico, cotizaciones, admin y visualizador. | C7: Errores detectados, performance pendiente y QA final.
A8: Actuar | B8: Optimizar selector de colores, carga 3D, textos, seguridad, datos reales y lanzamiento. | C8: Version lista para produccion y mejora continua.

Sheet Carta Gantt
A1: Carta Gantt - Proyecto desde cero
A2: Plan estimado de 12 semanas ejecutado por un programador.
A4: Actividad | B4: Area | C4: Inicio | D4: Fin | E4: Horas | F4: Estado | G4: Notas | H4: Avance | I4: S1 | J4: S2 | K4: S3 | L4: S4 | M4: S5 | N4: S6 | O4: S7 | P4: S8 | Q4: S9 | R4: S10 | S4: S11 | T4: S12
A5: Descubrimiento y definicion comercial | B5: Planificacion | C5: 1 | D5: 1 | E5: 18 | F5: Completado | G5: Objetivo, alcance, categorias, flujo comercial, estructura de BD. | H5: 1 | J5: ■
A6: Arquitectura Next.js y base UI | B6: Frontend | C6: 1 | D6: 2 | E6: 38 | F6: Completado | G6: App Router, Tailwind v4, layout publico, navegacion y base visual. | H6: 1 | J6: ■ | K6: ■
A7: Modelo de datos Supabase | B7: Backend/BD | C7: 2 | D7: 3 | E7: 34 | F7: Completado | G7: Productos, cotizaciones, settings, modelos 3D, policies y storage. | H7: 1 | K7: ■ | L7: ■
A8: Catalogo publico y categorias | B8: Frontend | C8: 3 | D8: 4 | E8: 34 | F8: Completado | G8: Listado de productos, colores, tallas, galeria e imagenes. | H8: 1 | L8: ■ | M8: ■
A9: Cotizador y carrito | B9: Producto | C9: 4 | D9: 6 | E9: 54 | F9: Completado | G9: Seleccion de tallas, cantidades, totales, datos cliente y generacion de cotizacion. | H9: 1 | M9: ■ | N9: ■ | O9: ■
A10: Panel admin productos | B10: Admin | C10: 5 | D10: 7 | E10: 46 | F10: Completado | G10: CRUD productos, imagenes, precios, colores, tallas y activacion. | H10: 1 | N10: ■ | O10: ■ | P10: ■
A11: Cotizaciones admin y email | B11: Admin/API | C11: 6 | D11: 8 | E11: 38 | F11: Completado | G11: Registro de cotizaciones, seguimiento, respuesta comercial y Resend. | H11: 1 | O11: ■ | P11: ■ | Q11: ■
A12: Branding, reglas comerciales y usuarios | B12: Admin/API | C12: 7 | D12: 9 | E12: 36 | F12: Completado | G12: Datos de marca, datos bancarios, descuentos, IVA, validez y usuarios. | H12: 1 | P12: ■ | Q12: ■ | R12: ■
A13: Visualizador 3D inicial | B13: 3D/WebGL | C13: 8 | D13: 9 | E13: 30 | F13: Completado | G13: R3F, Three, Fabric overlay, posiciones y carga de modelos. | H13: 1 | Q13: ■ | R13: ■
A14: Limpieza maniqui y prenda-only GLB | B14: 3D/WebGL | C14: 10 | D14: 10 | E14: 22 | F14: Completado | G14: Eliminacion del maniqui, dead code y enfoque en prenda GLB real. | H14: 1 | S14: ■
A15: QA tecnico lint/build/local | B15: QA | C15: 11 | D15: 11 | E15: 18 | F15: Completado | G15: Lint limpio, build exitoso, rutas 200 y captura local. | H15: 1 | T15: ■
A16: Optimizacion selector colores y carga 3D | B16: Performance | C16: 12 | D16: 12 | E16: 22 | F16: Pendiente | G16: Prefetch, cache, menor recomputo de texturas y mejor carga percibida. | H16: 0.15 | U16: ■
A17: QA final y preparacion produccion | B17: Lanzamiento | C17: 12 | D17: 12 | E17: 20 | F17: Pendiente | G17: Prueba end-to-end, variables, seguridad, datos reales y checklist final. | H17: 0.15 | U17: ■

Sheet Horas Programador
A1: Horas de programacion estimadas
A2: Trabajo realizado por un solo programador full-stack.
A4: Fase | B4: Horas | C4: Tarifa | D4: Costo | E4: % del total | F4: Descripcion
A5: Descubrimiento y definicion comercial | B5: 18 | C5: =Supuestos!$B$7 -> 18000 | D5: =B5*C5 -> 324000 | E5: =B5/SUM($B$5:$B$17) -> 0.043902439 | F5: Objetivo, alcance, categorias, flujo comercial, estructura de BD.
A6: Arquitectura Next.js y base UI | B6: 38 | C6: =Supuestos!$B$7 -> 18000 | D6: =B6*C6 -> 684000 | E6: =B6/SUM($B$5:$B$17) -> 0.092682927 | F6: App Router, Tailwind v4, layout publico, navegacion y base visual.
A7: Modelo de datos Supabase | B7: 34 | C7: =Supuestos!$B$7 -> 18000 | D7: =B7*C7 -> 612000 | E7: =B7/SUM($B$5:$B$17) -> 0.082926829 | F7: Productos, cotizaciones, settings, modelos 3D, policies y storage.
A8: Catalogo publico y categorias | B8: 34 | C8: =Supuestos!$B$7 -> 18000 | D8: =B8*C8 -> 612000 | E8: =B8/SUM($B$5:$B$17) -> 0.082926829 | F8: Listado de productos, colores, tallas, galeria e imagenes.
A9: Cotizador y carrito | B9: 54 | C9: =Supuestos!$B$7 -> 18000 | D9: =B9*C9 -> 972000 | E9: =B9/SUM($B$5:$B$17) -> 0.13170732 | F9: Seleccion de tallas, cantidades, totales, datos cliente y generacion de cotizacion.
A10: Panel admin productos | B10: 46 | C10: =Supuestos!$B$7 -> 18000 | D10: =B10*C10 -> 828000 | E10: =B10/SUM($B$5:$B$17) -> 0.11219512 | F10: CRUD productos, imagenes, precios, colores, tallas y activacion.
A11: Cotizaciones admin y email | B11: 38 | C11: =Supuestos!$B$7 -> 18000 | D11: =B11*C11 -> 684000 | E11: =B11/SUM($B$5:$B$17) -> 0.092682927 | F11: Registro de cotizaciones, seguimiento, respuesta comercial y Resend.
A12: Branding, reglas comerciales y usuarios | B12: 36 | C12: =Supuestos!$B$7 -> 18000 | D12: =B12*C12 -> 648000 | E12: =B12/SUM($B$5:$B$17) -> 0.087804878 | F12: Datos de marca, datos bancarios, descuentos, IVA, validez y usuarios.
A13: Visualizador 3D inicial | B13: 30 | C13: =Supuestos!$B$7 -> 18000 | D13: =B13*C13 -> 540000 | E13: =B13/SUM($B$5:$B$17) -> 0.073170732 | F13: R3F, Three, Fabric overlay, posiciones y carga de modelos.
A14: Limpieza maniqui y prenda-only GLB | B14: 22 | C14: =Supuestos!$B$7 -> 18000 | D14: =B14*C14 -> 396000 | E14: =B14/SUM($B$5:$B$17) -> 0.053658537 | F14: Eliminacion del maniqui, dead code y enfoque en prenda GLB real.
A15: QA tecnico lint/build/local | B15: 18 | C15: =Supuestos!$B$7 -> 18000 | D15: =B15*C15 -> 324000 | E15: =B15/SUM($B$5:$B$17) -> 0.043902439 | F15: Lint limpio, build exitoso, rutas 200 y captura local.
A16: Optimizacion selector colores y carga 3D | B16: 22 | C16: =Supuestos!$B$7 -> 18000 | D16: =B16*C16 -> 396000 | E16: =B16/SUM($B$5:$B$17) -> 0.053658537 | F16: Prefetch, cache, menor recomputo de texturas y mejor carga percibida.
A17: QA final y preparacion produccion | B17: 20 | C17: =Supuestos!$B$7 -> 18000 | D17: =B17*C17 -> 360000 | E17: =B17/SUM($B$5:$B$17) -> 0.048780488 | F17: Prueba end-to-end, variables, seguridad, datos reales y checklist final.
A18: TOTAL | B18: =SUM(B5:B17) -> 410 | D18: =SUM(D5:D17) -> 7380000 | E18: =SUM(E5:E17) -> 1

Sheet Costos Proyecto
A1: Costos del proyecto y operacion
A2: Incluye desarrollo, 3D, QA, assets y operacion mensual. No incluye Docker ni maquina virtual.
A4: Item | B4: Categoria | C4: Unidad | D4: Cantidad | E4: Costo unitario | F4: Total
A5: Programacion full-stack | B5: Implementacion | C5: Horas | D5: 280 | E5: =Supuestos!$B$7 -> 18000 | F5: =D5*E5 -> 5040000
A6: Diseno UX/UI aplicado | B6: Implementacion | C6: Horas | D6: 36 | E6: =Supuestos!$B$7 -> 18000 | F6: =D6*E6 -> 648000
A7: Modelos/prendas 3D y calibracion | B7: Implementacion | C7: Horas | D7: 42 | E7: =Supuestos!$B$7 -> 18000 | F7: =D7*E7 -> 756000
A8: QA, depuracion y limpieza tecnica | B8: Implementacion | C8: Horas | D8: 52 | E8: =Supuestos!$B$7 -> 18000 | F8: =D8*E8 -> 936000
A9: Dominio anual | B9: Operacion | C9: Anual | D9: 1 | E9: 15000 | F9: =D9*E9 -> 15000
A10: Vercel hosting | B10: Operacion | C10: Mensual | D10: 1 | E10: 0 | F10: =D10*E10 -> 0
A11: Supabase | B11: Operacion | C11: Mensual | D11: 1 | E11: 0 | F11: =D11*E11 -> 0
A12: Resend/email | B12: Operacion | C12: Mensual | D12: 1 | E12: 0 | F12: =D12*E12 -> 0
A13: Produccion fotografica/assets | B13: Marketing | C13: Unico | D13: 1 | E13: 180000 | F13: =D13*E13 -> 180000
A14: Modelado 3D adicional futuro | B14: Marketing/3D | C14: Por modelo | D14: 8 | E14: 35000 | F14: =D14*E14 -> 280000
A15: Mantencion mensual tecnica | B15: Operacion | C15: Mensual | D15: 8 | E15: 18000 | F15: =D15*E15 -> 144000
A16: Operacion comercial mensual | B16: Operacion | C16: Mensual | D16: 12 | E16: 12000 | F16: =D16*E16 -> 144000
A18: Resumen
A19: Costo desarrollo estimado | F19: =SUM(F5:F8) -> 7380000
A20: Costos unicos adicionales | F20: =SUM(F9:F13) -> 195000
A21: Costo operativo mensual base | F21: =SUM(F14:F16) -> 568000

Sheet Flujo Caja
A1: Flujo de caja operativo estimado
A2: Modelo editable con anticipo, saldo contra entrega, costos variables y costos fijos.
A4: Mes | B4: Cotizaciones | C4: Conversion | D4: Pedidos | E4: Ticket prom. | F4: Ingresos brutos | G4: Anticipos 60% | H4: Saldos 40% | I4: Costo variable | J4: Costo fijo | K4: Caja neta | M4: Mes | N4: Caja neta
A5: Mes 1 | B5: 12 | C5: 0.18 | D5: =ROUND(B5*C5,0) -> 2 | E5: =Supuestos!$B$14 -> 650000 | F5: =D5*E5 -> 1300000 | G5: =F5*Supuestos!$B$11 -> 780000 | H5: =F5*Supuestos!$B$12 -> 520000 | I5: =F5*(1-Supuestos!$B$13) -> 715000 | J5: ='Costos Proyecto'!$F$21 -> 568000 | K5: =G5+H5-I5-J5 -> 17000 | M5: Mes 1 | N5: =K5 -> 17000
A6: Mes 2 | B6: 18 | C6: 0.28 | D6: =ROUND(B6*C6,0) -> 5 | E6: =Supuestos!$B$14 -> 650000 | F6: =D6*E6 -> 3250000 | G6: =F6*Supuestos!$B$11 -> 1950000 | H6: =F6*Supuestos!$B$12 -> 1300000 | I6: =F6*(1-Supuestos!$B$13) -> 1787500 | J6: ='Costos Proyecto'!$F$21 -> 568000 | K6: =G6+H6-I6-J6 -> 894500 | M6: Mes 2 | N6: =K6 -> 894500
A7: Mes 3 | B7: 24 | C7: 0.33 | D7: =ROUND(B7*C7,0) -> 8 | E7: =Supuestos!$B$14 -> 650000 | F7: =D7*E7 -> 5200000 | G7: =F7*Supuestos!$B$11 -> 3120000 | H7: =F7*Supuestos!$B$12 -> 2080000 | I7: =F7*(1-Supuestos!$B$13) -> 2860000 | J7: ='Costos Proyecto'!$F$21 -> 568000 | K7: =G7+H7-I7-J7 -> 1772000 | M7: Mes 3 | N7: =K7 -> 1772000
A8: Mes 4 | B8: 30 | C8: 0.36 | D8: =ROUND(B8*C8,0) -> 11 | E8: =Supuestos!$B$14 -> 650000 | F8: =D8*E8 -> 7150000 | G8: =F8*Supuestos!$B$11 -> 4290000 | H8: =F8*Supuestos!$B$12 -> 2860000 | I8: =F8*(1-Supuestos!$B$13) -> 3932500 | J8: ='Costos Proyecto'!$F$21 -> 568000 | K8: =G8+H8-I8-J8 -> 2649500 | M8: Mes 4 | N8: =K8 -> 2649500
A9: Mes 5 | B9: 36 | C9: 0.38 | D9: =ROUND(B9*C9,0) -> 14 | E9: =Supuestos!$B$14 -> 650000 | F9: =D9*E9 -> 9100000 | G9: =F9*Supuestos!$B$11 -> 5460000 | H9: =F9*Supuestos!$B$12 -> 3640000 | I9: =F9*(1-Supuestos!$B$13) -> 5005000 | J9: ='Costos Proyecto'!$F$21 -> 568000 | K9: =G9+H9-I9-J9 -> 3527000 | M9: Mes 5 | N9: =K9 -> 3527000
A10: Mes 6 | B10: 42 | C10: 0.4 | D10: =ROUND(B10*C10,0) -> 17 | E10: =Supuestos!$B$14 -> 650000 | F10: =D10*E10 -> 11050000 | G10: =F10*Supuestos!$B$11 -> 6630000 | H10: =F10*Supuestos!$B$12 -> 4420000 | I10: =F10*(1-Supuestos!$B$13) -> 6077500 | J10: ='Costos Proyecto'!$F$21 -> 568000 | K10: =G10+H10-I10-J10 -> 4404500 | M10: Mes 6 | N10: =K10 -> 4404500
A12: TOTAL 6 MESES | B12: =SUM(B5:B10) -> 162 | C12: =AVERAGE(C5:C10) -> 0.32166667 | D12: =SUM(D5:D10) -> 57 | E12: =AVERAGE(E5:E10) -> 650000 | F12: =SUM(F5:F10) -> 37050000 | G12: =SUM(G5:G10) -> 22230000 | H12: =SUM(H5:H10) -> 14820000 | I12: =SUM(I5:I10) -> 20377500 | J12: =SUM(J5:J10) -> 3408000 | K12: =SUM(K5:K10) -> 13264500

Sheet Alcance y Entregables
A1: Alcance realizado y pendientes
A2: Recopilacion del proyecto ejecutado.
A4: Modulo | B4: Estado | C4: Detalle
A5: Base de datos Supabase | B5: Realizado | C5: Products, quotes, settings, product_models, users/auth, storage y RLS.
A6: Sitio publico | B6: Realizado | C6: Inicio, quienes somos, servicios, medidas/cuidados y categorias.
A7: Cotizador | B7: Realizado | C7: Colores, tallas, cantidades, carrito, datos cliente, totales y envio.
A8: Admin productos | B8: Realizado | C8: CRUD, imagenes, tallas, colores, precios, mayorista y estado activo.
A9: Admin cotizaciones | B9: Realizado | C9: Listado, detalle, estado, respuesta y seguimiento.
A10: Branding y reglas | B10: Realizado | C10: Datos empresa, bancos, IVA, descuento, validez y condiciones.
A11: Usuarios admin | B11: Realizado | C11: Gestion de usuarios y roles via Supabase Auth.
A12: Modelos 3D | B12: Realizado | C12: Carga GLB/GLTF, asociacion a producto y calibracion.
A13: Visualizador 3D | B13: Realizado | C13: Prenda-only GLB sin maniqui; limpieza de dead code.
A14: Email | B14: Realizado | C14: Route Handler con Resend para cotizacion y respuesta admin.
A15: QA tecnico | B15: Realizado | C15: Lint limpio, build OK y pruebas locales 200.
... A18: Medicion comercial | B18: Pendiente | C18: KPIs: cotizaciones, conversion, ticket promedio, margen y tiempos de respuesta.
